[
    {
        "Category": "Cricket",
        "League": "Cricket",
        "Team 1 Name": "",
        "Team 2 Name": "",
        "Team 1 Logo": "",
        "Team 2 Logo": "",
        "Match Title": "Willow Cricket",
        "Match Poster": "https://streamed.pk/api/images/proxy/GwZg7AZpYEZgHCAjAJgCzuAQ2C4+cBjYAUwRQFYxi8xg61rLoATdMFSCiUME-YAE5gFbLnrlGUGtB5lBFRvPqVgSWMEJ58fBJCGlxo+BP5zgEIA.webp",
        "Match Status": "Upcoming ⏳",
        "Start Time": "",
        "User-Agent": "Mozilla/5.0 (Windows NT 10.0; Win64; x64)",
        "Streams": [
            {
                "Source": "admin",
                "Stream_No": 1,
                "Language": "English",
                "Quality": "HD",
                "Embed_URL": "https://embedsports.top/embed/admin/admin-willow-cricket/1"
            },
            {
                "Source": "admin",
                "Stream_No": 2,
                "Language": "Willow 2",
                "Quality": "HD",
                "Embed_URL": "https://embedsports.top/embed/admin/admin-willow-cricket/2"
            },
            {
                "Source": "admin",
                "Stream_No": 3,
                "Language": "Willow Sports",
                "Quality": "HD",
                "Embed_URL": "https://embedsports.top/embed/admin/admin-willow-cricket/3"
            }
        ]
    },
    {
        "Category": "Motor-sports",
        "League": "Motor-sports",
        "Team 1 Name": "",
        "Team 2 Name": "",
        "Team 1 Logo": "",
        "Team 2 Logo": "",
        "Match Title": "Rally TV",
        "Match Poster": "https://streamed.pk/api/images/proxy/GwZg7AZpYEZgHCAjAJgCzuMFBWLwBTYCbYAQxSzPzLCWDWB12Hga00quAGNCF0GdCBQhqjEM1Y4AJhixo5YXLCa8uwMAQSRgATkKk8bMFuKGIQA.webp",
        "Match Status": "Upcoming ⏳",
        "Start Time": "",
        "User-Agent": "Mozilla/5.0 (Windows NT 10.0; Win64; x64)",
        "Streams": [
            {
                "Source": "admin",
                "Stream_No": 1,
                "Language": "English",
                "Quality": "HD",
                "Embed_URL": "https://embedsports.top/embed/admin/admin-rally-tv/1"
            }
        ]
    },
    {
        "Category": "Tennis",
        "League": "Tennis",
        "Team 1 Name": "",
        "Team 2 Name": "",
        "Team 1 Logo": "",
        "Team 2 Logo": "",
        "Match Title": "ATP/WTA 1000: Madrid 🎾",
        "Match Poster": "https://placehold.co/800x450/1a1a1a/ffffff.png?text=ATP/WTA%201000%3A%20Madrid%20%F0%9F%8E%BE&font=Oswald",
        "Match Status": "Upcoming ⏳",
        "Start Time": "06:00 PM | 04-May",
        "User-Agent": "Mozilla/5.0 (Windows NT 10.0; Win64; x64)",
        "Streams": [
            {
                "Source": "echo",
                "Stream_No": 1,
                "Language": "",
                "Quality": "HD",
                "Embed_URL": "https://embedsports.top/embed/echo/atpwta-1000-madrid-tn-1/1"
            },
            {
                "Source": "echo",
                "Stream_No": 2,
                "Language": "",
                "Quality": "HD",
                "Embed_URL": "https://embedsports.top/embed/echo/atpwta-1000-madrid-tn-1/2"
            },
            {
                "Source": "echo",
                "Stream_No": 3,
                "Language": "",
                "Quality": "HD",
                "Embed_URL": "https://embedsports.top/embed/echo/atpwta-1000-madrid-tn-1/3"
            },
            {
                "Source": "echo",
                "Stream_No": 4,
                "Language": "",
                "Quality": "HD",
                "Embed_URL": "https://embedsports.top/embed/echo/atpwta-1000-madrid-tn-1/4"
            },
            {
                "Source": "echo",
                "Stream_No": 5,
                "Language": "",
                "Quality": "HD",
                "Embed_URL": "https://embedsports.top/embed/echo/atpwta-1000-madrid-tn-1/5"
            }
        ]
    },
    {
        "Category": "Football",
        "League": "Football",
        "Team 1 Name": "Chelsea",
        "Team 2 Name": "Nottingham Forest",
        "Team 1 Logo": "https://streamed.pk/api/images/proxy/GwZg7AZpYEZgHCAjAJgCzrAThFlBWSUYAUwVmDW2nmAmD32FrWGHXbeAENgBjUgg5sSdTt0z1Rvdqyw8xAkphRgAJmD7roJENxAQDIY8f2Ic+5YRjAmfFFzBl4ReaIdNaYJ2NEQgA.webp",
        "Team 2 Logo": "https://streamed.pk/api/images/proxy/GwZg7AZpYEZgHCAjAJgCzrAThFlBWSUYAUwVmDW2nmAmD32FrWGHXbeAENgBjUgg5sSdTt0z1Rvdqyw8xAkh3kAGEFF5IEIbiBIaQAE0MQQMEIgMTCMYEz4ouYMvCLzRTprTAuxoiCA.webp",
        "Match Title": "Chelsea vs Nottingham Forest",
        "Match Poster": "https://streamed.pk/api/images/proxy/GwZg7AZpYEZgHCAjAJgCzrAThFlBWSUYAUwVmDW2nmAmD32FrWGHXbeAENgBjUgg5sSdTtw5kAJqWCEImeuFFs8aELzAUQxRNxB8QJEDBCIcplCCsKmSCn2Gz6KMCpRc35ellkemtFqi9MFAA.webp",
        "Match Status": "Upcoming ⏳",
        "Start Time": "08:00 PM | 04-May",
        "User-Agent": "Mozilla/5.0 (Windows NT 10.0; Win64; x64)",
        "Streams": [
            {
                "Source": "admin",
                "Stream_No": 1,
                "Language": "English - Sky Sports Premier League",
                "Quality": "HD",
                "Embed_URL": "https://embedsports.top/embed/admin/ppv-chelsea-vs-nottingham-forest/1"
            },
            {
                "Source": "admin",
                "Stream_No": 2,
                "Language": "English - Sky Sports Premier League",
                "Quality": "SD",
                "Embed_URL": "https://embedsports.top/embed/admin/ppv-chelsea-vs-nottingham-forest/2"
            },
            {
                "Source": "golf",
                "Stream_No": 1,
                "Language": "English",
                "Quality": "HD",
                "Embed_URL": "https://embedsports.top/embed/golf/22110/1"
            }
        ]
    },
    {
        "Category": "Cricket",
        "League": "Cricket",
        "Team 1 Name": "Mumbai Indians",
        "Team 2 Name": "Lucknow Super Giants",
        "Team 1 Logo": "https://streamed.pk/api/images/proxy/GwZg7AZpYEZgHCAjAJgCzrAThFlBWSUYAUwVmDW2nmAmD32FrWGHXbeAENgBjUgg5sSdTt0z1Rvdqyw8xAkhzAgIIGMCQhwMENzU6QfEABNjR84gmFNTPii5gy8IvNGOmtMM7GiIQA.webp",
        "Team 2 Logo": "https://streamed.pk/api/images/proxy/GwZg7AZpYEZgHCAjAJgCzrAThFlBWSUYAUwVmDW2nmAmD32FrWGHXbeAENgBjUgg5sSdTt0z1Rvdqyw8xAkuhBQoSLgBMeIbiE2qQfQxBAkQFxCgIUmfFFzBl4ReaIdNaYJ2NEQgA.webp",
        "Match Title": "Mumbai Indians vs Lucknow Super Giants",
        "Match Poster": "https://streamed.pk/api/images/proxy/GwZg7AZpYEZgHCAjAJgCzrAThFlBWSUYAUwVmDW2nmAmD32FrWGHXbeAENgBjUgg5sSdTtw5kAJqWCEImeuFFs8rUWSxgpIFiG4g++3CB06YJnPALAkFPsNn0UYFSi6vy9LLPdNaYK5iohBAA.webp",
        "Match Status": "Upcoming ⏳",
        "Start Time": "08:00 PM | 04-May",
        "User-Agent": "Mozilla/5.0 (Windows NT 10.0; Win64; x64)",
        "Streams": [
            {
                "Source": "admin",
                "Stream_No": 1,
                "Language": "English - Indian Premier League",
                "Quality": "HD",
                "Embed_URL": "https://embedsports.top/embed/admin/ppv-mumbai-indians-vs-lucknow-super-giants/1"
            },
            {
                "Source": "admin",
                "Stream_No": 2,
                "Language": "English - Indian Premier League",
                "Quality": "SD",
                "Embed_URL": "https://embedsports.top/embed/admin/ppv-mumbai-indians-vs-lucknow-super-giants/2"
            }
        ]
    },
    {
        "Category": "Golf",
        "League": "Golf",
        "Team 1 Name": "",
        "Team 2 Name": "",
        "Team 1 Logo": "",
        "Team 2 Logo": "",
        "Match Title": "Cadillac Championship | PGA Tour",
        "Match Poster": "https://placehold.co/800x450/1a1a1a/ffffff.png?text=Cadillac%20Championship%20%7C%20PGA%20Tour&font=Oswald",
        "Match Status": "Upcoming ⏳",
        "Start Time": "09:00 PM | 04-May",
        "User-Agent": "Mozilla/5.0 (Windows NT 10.0; Win64; x64)",
        "Streams": [
            {
                "Source": "echo",
                "Stream_No": 1,
                "Language": "",
                "Quality": "HD",
                "Embed_URL": "https://embedsports.top/embed/echo/cadillac-championship-pga-tour-pga-526234/1"
            },
            {
                "Source": "echo",
                "Stream_No": 2,
                "Language": "",
                "Quality": "HD",
                "Embed_URL": "https://embedsports.top/embed/echo/cadillac-championship-pga-tour-pga-526234/2"
            },
            {
                "Source": "echo",
                "Stream_No": 3,
                "Language": "",
                "Quality": "HD",
                "Embed_URL": "https://embedsports.top/embed/echo/cadillac-championship-pga-tour-pga-526234/3"
            },
            {
                "Source": "echo",
                "Stream_No": 4,
                "Language": "",
                "Quality": "HD",
                "Embed_URL": "https://embedsports.top/embed/echo/cadillac-championship-pga-tour-pga-526234/4"
            }
        ]
    },
    {
        "Category": "Football",
        "League": "Football",
        "Team 1 Name": "Cremonese",
        "Team 2 Name": "Lazio",
        "Team 1 Logo": "https://streamed.pk/api/images/proxy/GwZg7AZpYEZgHCAjAJgCzrAThFlBWSUYAUwVmDW2nmAmD32FrWGHXbeAENgBjUgg5sSdTt0z1Rvdqyw8xAkuhAATYEz64wqsChDcQJEFv1aYISzn0TCMDfxRcwZeEXminTWmBdjREEA.webp",
        "Team 2 Logo": "https://streamed.pk/api/images/proxy/GwZg7AZpYEZgHCAjAJgCzrAThFlBWSUYAUwVmDW2nmAmD32FrWGHXbeAENgBjUgg5sSdTt0z1Rvdqyw8xAkpixg+YbmBRgAJghDcQEIyFOmYIHZZAWQBCkz4ouYMvCLzRzprTCuxohBAA.webp",
        "Match Title": "Cremonese vs Lazio",
        "Match Poster": "https://streamed.pk/api/images/proxy/GwZg7AZpYEZgHCAjAJgCzrAThFlBWSUYAUwVmDW2nmAmD32FrWGHXbeAENgBjUgg5sSdTtw5kAJqWCEImeuFFs8VHFjBJgABmBSwfENxBGSIcyhCJzMUyBQFgSCn2Gz6KMCpRdv5eixZXyZaMG8xUQggA.webp",
        "Match Status": "Upcoming ⏳",
        "Start Time": "10:30 PM | 04-May",
        "User-Agent": "Mozilla/5.0 (Windows NT 10.0; Win64; x64)",
        "Streams": [
            {
                "Source": "admin",
                "Stream_No": 1,
                "Language": "English - Paramount+",
                "Quality": "HD",
                "Embed_URL": "https://embedsports.top/embed/admin/ppv-cremonese-vs-lazio/1"
            },
            {
                "Source": "admin",
                "Stream_No": 2,
                "Language": "English - Paramount+",
                "Quality": "SD",
                "Embed_URL": "https://embedsports.top/embed/admin/ppv-cremonese-vs-lazio/2"
            }
        ]
    },
    {
        "Category": "Football",
        "League": "Football",
        "Team 1 Name": "Roma",
        "Team 2 Name": "Fiorentina",
        "Team 1 Logo": "https://streamed.pk/api/images/proxy/GwZg7AZpYEZgHCAjAJgCzrAThFlBWSUYAUwVmDW2nmAmD32FrWGHXbeAENgBjUgg5sSdTt0z1Rvdqyw8xAkhyRg+2SrgQhuIPiAAmIGCFM4TR-RAIUmfFFzBl4ReaIdNaYJ2NEQgA.webp",
        "Team 2 Logo": "https://streamed.pk/api/images/proxy/GwZg7AZpYEZgHCAjAJgCzrAThFlBWSUYAUwVmDW2nmAmD32FrWGHXbeAENgBjUgg5sSdTt0z1Rvdqyw8xAkhxDMQqpuBIhuIACYhtBmCBTqQJxDAIUmfFFzBl4ReaIdNaYJ2NEQgA.webp",
        "Match Title": "Roma vs Fiorentina",
        "Match Poster": "https://streamed.pk/api/images/proxy/GwZg7AZpYEZgHCAjAJgCzrAThFlBWSUYAUwVmDW2nmAmD32FrWGHXbeAENgBjUgg5sSdTtw5kAJqWCEImeuFFs8aECjACmZcNxD6+IKSBIgI53MetSCwJBT7DZ9TSpRcwZeESyyPTLRgXmKiEEA.webp",
        "Match Status": "Upcoming ⏳",
        "Start Time": "12:45 AM | 05-May",
        "User-Agent": "Mozilla/5.0 (Windows NT 10.0; Win64; x64)",
        "Streams": [
            {
                "Source": "admin",
                "Stream_No": 1,
                "Language": "English - Paramount+",
                "Quality": "HD",
                "Embed_URL": "https://embedsports.top/embed/admin/ppv-as-roma-vs-fiorentina/1"
            },
            {
                "Source": "admin",
                "Stream_No": 2,
                "Language": "English - Paramount+",
                "Quality": "SD",
                "Embed_URL": "https://embedsports.top/embed/admin/ppv-as-roma-vs-fiorentina/2"
            }
        ]
    },
    {
        "Category": "Football",
        "League": "Football",
        "Team 1 Name": "Sevilla",
        "Team 2 Name": "Real Sociedad",
        "Team 1 Logo": "https://streamed.pk/api/images/proxy/GwZg7AZpYEZgHCAjAJgCzrAThFlBWSUYAUwVmDW2nmAmD32FrWGHXbeAENgBjUgg5sSdTt0z1Rvdqyw8xAkpgAmsctzCaQIbiAgg+IRCRAxcIFIcMEKTPii5gy8IvNGOmtMM7GiIQA.webp",
        "Team 2 Logo": "https://streamed.pk/api/images/proxy/GwZg7AZpYEZgHCAjAJgCzrAThFlBWSUYAUwVmDW2nmAmD32FrWGHXbeAENgBjUgg5sSdTt0z1Rvdqyw8xAkpgAmsaGrg5uICCD4hEJEDFwgUISyoIUmfFFzBl4ReaIdNaYJ2NEQgA.webp",
        "Match Title": "Sevilla vs Real Sociedad",
        "Match Poster": "https://streamed.pk/api/images/proxy/GwZg7AZpYEZgHCAjAJgCzrAThFlBWSUYAUwVmDW2nmAmD32FrWGHXbeAENgBjUgg5sSdTtw5kAJqWCEImeuFFs8rJNhDcwKMEhAQtIPiBJHDZmCEQnGwDTH7DZ9XSpRcwZeESyyPTLRgXmKiEEA.webp",
        "Match Status": "Upcoming ⏳",
        "Start Time": "01:00 AM | 05-May",
        "User-Agent": "Mozilla/5.0 (Windows NT 10.0; Win64; x64)",
        "Streams": [
            {
                "Source": "admin",
                "Stream_No": 1,
                "Language": "English - LaLigaTV",
                "Quality": "HD",
                "Embed_URL": "https://embedsports.top/embed/admin/ppv-sevilla-vs-real-sociedad/1"
            },
            {
                "Source": "admin",
                "Stream_No": 2,
                "Language": "English - LaLigaTV",
                "Quality": "SD",
                "Embed_URL": "https://embedsports.top/embed/admin/ppv-sevilla-vs-real-sociedad/2"
            }
        ]
    },
    {
        "Category": "Football",
        "League": "Football",
        "Team 1 Name": "Everton",
        "Team 2 Name": "Manchester City",
        "Team 1 Logo": "https://streamed.pk/api/images/proxy/GwZg7AZpYEZgHCAjAJgCzrAThFlBWSUYAUwVmDW2nmAmD32FrWGHXbeAENgBjUgg5sSdTt0z1Rvdqyw8xAkhzK9uYFNmAATENxAlcIRPpAgIIPiBTmCFJnxRcwZeEXminTWmBdjREEA.webp",
        "Team 2 Logo": "https://streamed.pk/api/images/proxy/GwZg7AZpYEZgHCAjAJgCzrAThFlBWSUYAUwVmDW2nmAmD32FrWGHXbeAENgBjUgg5sSdTt0z1Rvdqyw8xAkpgAmYPrDBqsYFCG4gIIFSD6HjuCyX0EKTPii5gy8IvNGOmtMM7GiIQA.webp",
        "Match Title": "Everton vs Manchester City",
        "Match Poster": "https://streamed.pk/api/images/proxy/GwZg7AZpYEZgHCAjAJgCzrAThFlBWSUYAUwVmDW2nmAmD32FrWGHXbeAENgBjUgg5sSdTtw5kAJqWCEImeuFFs8aXCFFYGYPthDcQfTSBghEOMyhDW+BYEgp3WIsSjAqUXD+XrbRXky0YB5iohBAA.webp",
        "Match Status": "Upcoming ⏳",
        "Start Time": "01:00 AM | 05-May",
        "User-Agent": "Mozilla/5.0 (Windows NT 10.0; Win64; x64)",
        "Streams": [
            {
                "Source": "admin",
                "Stream_No": 1,
                "Language": "English - Sky Sports Premier League",
                "Quality": "HD",
                "Embed_URL": "https://embedsports.top/embed/admin/ppv-everton-vs-manchester-city/1"
            },
            {
                "Source": "admin",
                "Stream_No": 2,
                "Language": "English - Sky Sports Premier League",
                "Quality": "SD",
                "Embed_URL": "https://embedsports.top/embed/admin/ppv-everton-vs-manchester-city/2"
            },
            {
                "Source": "golf",
                "Stream_No": 1,
                "Language": "English",
                "Quality": "HD",
                "Embed_URL": "https://embedsports.top/embed/golf/22111/1"
            }
        ]
    },
    {
        "Category": "Baseball",
        "League": "Baseball",
        "Team 1 Name": "Colorado Rockies",
        "Team 2 Name": "New York Mets",
        "Team 1 Logo": "https://streamed.pk/api/images/proxy/GwZg7AZpYEZgHCAjAJgCzrAThFlBWSUYAUwVmDW2nmAmD32FrWGHXbeAENgBjUgg5sSdTt0z1Rvdqyw8xAkphx8w3EABNgABkogNmkMb5aQMYyEQoQywjGBM+KLmDLwi80S6a0wbsVEIIA.webp",
        "Team 2 Logo": "https://streamed.pk/api/images/proxy/GwZg7AZpYEZgHCAjAJgCzrAThFlBWSUYAUwVmDW2nmAmD32FrWGHXbeAENgBjUgg5sSdTt0z1Rvdqyw8xAkpixhw3cnG4htEEIm0kQemPrN8CFJha5gy8IvNEpgTWmDtjREIA.webp",
        "Match Title": "Colorado Rockies vs New York Mets",
        "Match Poster": "https://streamed.pk/api/images/proxy/GwZg7AZpYEZgHCAjAJgCzrAY29lBWSUYAUwVmDTAE5p5gJhqDh61hh1OPgBDYLKQRcOJBt15cyAE1LBCETI3BiOzdmEqsGNENJC8QWIyZIgIeyyGsskFLCLmMUYVSh6vyjanPf5tYK7iYhBAA.webp",
        "Match Status": "Upcoming ⏳",
        "Start Time": "03:40 AM | 05-May",
        "User-Agent": "Mozilla/5.0 (Windows NT 10.0; Win64; x64)",
        "Streams": [
            {
                "Source": "admin",
                "Stream_No": 1,
                "Language": "English - Rockies.TV",
                "Quality": "HD",
                "Embed_URL": "https://embedsports.top/embed/admin/ppv-new-york-mets-vs-colorado-rockies/1"
            },
            {
                "Source": "admin",
                "Stream_No": 2,
                "Language": "English - Rockies.TV",
                "Quality": "SD",
                "Embed_URL": "https://embedsports.top/embed/admin/ppv-new-york-mets-vs-colorado-rockies/2"
            },
            {
                "Source": "golf",
                "Stream_No": 1,
                "Language": "English",
                "Quality": "HD",
                "Embed_URL": "https://embedsports.top/embed/golf/22162/1"
            }
        ]
    },
    {
        "Category": "Baseball",
        "League": "Baseball",
        "Team 1 Name": "Detroit Tigers",
        "Team 2 Name": "Boston Red Sox",
        "Team 1 Logo": "https://streamed.pk/api/images/proxy/GwZg7AZpYEZgHCAjAJgCzrAThFlBWSUYAUwVmDW2nmAmD32FrWGHXbeAENgBjUgg5sSdTt0z1Rvdqyw8xAkuhAoxanABNKIbiBL6QEEDBCIcevmYIUmfNWzBl4ReaLVNaYJ2NEQgA.webp",
        "Team 2 Logo": "https://streamed.pk/api/images/proxy/GwZg7AZpYEZgHCAjAJgCzrAThFlBWSUYAUwVmDW2nmAmD32FrWGHXbeAENgBjUgg5sSdTt0z1Rvdqyw8xAkpnjQ4qsom4gIuECRDacMPduWEYwJnxRcwmovNG2mtMPbGiIQA.webp",
        "Match Title": "Detroit Tigers vs Boston Red Sox",
        "Match Poster": "https://streamed.pk/api/images/proxy/GwZg7AZpYEZgHCAjAJgCzrAY29lBWSUYAUwVmDTAE5p5gJhqDh61hh1OPgBDYLKQRcOJBt15cyAE1LBCETI3BiOzdgAYmICCBWsQvEFmOmSOkNMt7jLJBSwi5jFGFUoeb8o2pyP+VmAwN3ExCCA.webp",
        "Match Status": "Upcoming ⏳",
        "Start Time": "04:40 AM | 05-May",
        "User-Agent": "Mozilla/5.0 (Windows NT 10.0; Win64; x64)",
        "Streams": [
            {
                "Source": "admin",
                "Stream_No": 1,
                "Language": "English - Tigers.TV",
                "Quality": "HD",
                "Embed_URL": "https://embedsports.top/embed/admin/ppv-boston-red-sox-vs-detroit-tigers/1"
            },
            {
                "Source": "admin",
                "Stream_No": 2,
                "Language": "English - Tigers.TV",
                "Quality": "SD",
                "Embed_URL": "https://embedsports.top/embed/admin/ppv-boston-red-sox-vs-detroit-tigers/2"
            },
            {
                "Source": "golf",
                "Stream_No": 1,
                "Language": "English",
                "Quality": "HD",
                "Embed_URL": "https://embedsports.top/embed/golf/22154/1"
            }
        ]
    },
    {
        "Category": "Baseball",
        "League": "Baseball",
        "Team 1 Name": "Tampa Bay Rays",
        "Team 2 Name": "Toronto Blue Jays",
        "Team 1 Logo": "https://streamed.pk/api/images/proxy/GwZg7AZpYEZgHCAjAJgCzrAThFlBWSUYAUwVmDW2nmAmD32FrWGHXbeAENgBjUgg5sSdTt0z1Rvdqyw8xAkhzDtoUFJBDcQJXSAggYIRDoAmuEwQpM+KLmDLwi80faa0wjsaIhA.webp",
        "Team 2 Logo": "https://streamed.pk/api/images/proxy/GwZg7AZpYEZgHCAjAJgCzrAThFlBWSUYAUwVmDW2nmAmD32FrWGHXbeAENgBjUgg5sSdTt0z1Rvdqyw8xAkhwAmIFGCTAADCFpgQ3EGqN8QJXCDNqQxghSZ8UXMGXhF5o5032uxoiCA.webp",
        "Match Title": "Tampa Bay Rays vs Toronto Blue Jays",
        "Match Poster": "https://streamed.pk/api/images/proxy/GwZg7AZpYEZgHCAjAJgCzrAY29lBWSUYAUwVmDTAE5p5gJhqDh61hh1OPgBDYLKQRcOJBt15cyAE1LBCETI3BiOzKtISsQZMShC8QWIyZIgIIaZZMoWSClhFzGKMKpQ835RtTkf8rMBgbuJiEEA.webp",
        "Match Status": "Upcoming ⏳",
        "Start Time": "04:40 AM | 05-May",
        "User-Agent": "Mozilla/5.0 (Windows NT 10.0; Win64; x64)",
        "Streams": [
            {
                "Source": "admin",
                "Stream_No": 1,
                "Language": "English - Rays.TV",
                "Quality": "HD",
                "Embed_URL": "https://embedsports.top/embed/admin/ppv-toronto-blue-jays-vs-tampa-bay-rays/1"
            },
            {
                "Source": "admin",
                "Stream_No": 2,
                "Language": "English - Rays.TV",
                "Quality": "SD",
                "Embed_URL": "https://embedsports.top/embed/admin/ppv-toronto-blue-jays-vs-tampa-bay-rays/2"
            },
            {
                "Source": "golf",
                "Stream_No": 1,
                "Language": "English",
                "Quality": "HD",
                "Embed_URL": "https://embedsports.top/embed/golf/22156/1"
            }
        ]
    },
    {
        "Category": "Baseball",
        "League": "Baseball",
        "Team 1 Name": "Miami Marlins",
        "Team 2 Name": "Philadelphia Phillies",
        "Team 1 Logo": "https://streamed.pk/api/images/proxy/GwZg7AZpYEZgHCAjAJgCzrAThFlBWSUYAUwVmDW2nmAmD32FrWGHXbeAENgBjUgg5sSdTt0z1Rvdqyw8xAkuhAwQfXLmAATBCG4gSICCG2rzBjWomEYwJnxRcwZeEXminTWmBdjREEA.webp",
        "Team 2 Logo": "https://streamed.pk/api/images/proxy/GwZg7AZpYEZgHCAjAJgCzrAThFlBWSUYAUwVmDW2nmAmD32FrWGHXbeAENgBjUgg5sSdTt0z1Rvdqyw8xAkuhDww4eWDEATENxC79fECVwhzu84wpM+KLmDJr680faa0wjsaIhA.webp",
        "Match Title": "Miami Marlins vs Philadelphia Phillies",
        "Match Poster": "https://streamed.pk/api/images/proxy/GwZg7AZpYEZgHCAjAJgCzrAY29lBWSUYAUwVmDTAE5p5gJhqDh61hh1OPgBDYLKQRcOJBt15cyAE1LBCETI3BiOzdkgZhNIeQhC8QWIyZIgIIaZZMgWSClhFzGKMKpQ835RtTkf8rMBgbuJiEEA.webp",
        "Match Status": "Upcoming ⏳",
        "Start Time": "04:40 AM | 05-May",
        "User-Agent": "Mozilla/5.0 (Windows NT 10.0; Win64; x64)",
        "Streams": [
            {
                "Source": "admin",
                "Stream_No": 1,
                "Language": "English - Marlins.TV",
                "Quality": "HD",
                "Embed_URL": "https://embedsports.top/embed/admin/ppv-philadelphia-phillies-vs-miami-marlins/1"
            },
            {
                "Source": "admin",
                "Stream_No": 2,
                "Language": "English - Marlins.TV",
                "Quality": "SD",
                "Embed_URL": "https://embedsports.top/embed/admin/ppv-philadelphia-phillies-vs-miami-marlins/2"
            },
            {
                "Source": "golf",
                "Stream_No": 1,
                "Language": "English",
                "Quality": "HD",
                "Embed_URL": "https://embedsports.top/embed/golf/22155/1"
            }
        ]
    },
    {
        "Category": "Hockey",
        "League": "Hockey",
        "Team 1 Name": "Philadelphia Flyers",
        "Team 2 Name": "Carolina Hurricanes",
        "Team 1 Logo": "",
        "Team 2 Logo": "",
        "Match Title": "Philadelphia Flyers vs. Carolina Hurricanes",
        "Match Poster": "https://streamed.pk/api/images/proxy/GwZg7AZpYEZgHCAjAJgCzuAQ1sFKBWWYgE0OHjBEx0vmAFNp51JQwHguBOdEbkPRKD+ICKM7iBWMSBkNRwkMpCdEC+mpABjECWDDdM7gcYpgbcJx7AC2PBfJJc281w4I2Jzubv0wHMAQjEFAA.webp",
        "Match Status": "Upcoming ⏳",
        "Start Time": "05:00 AM | 05-May",
        "User-Agent": "Mozilla/5.0 (Windows NT 10.0; Win64; x64)",
        "Streams": [
            {
                "Source": "admin",
                "Stream_No": 1,
                "Language": "English - ESPN",
                "Quality": "HD",
                "Embed_URL": "https://embedsports.top/embed/admin/ppv-philadelphia-flyers-vs-carolina-hurricanes/1"
            },
            {
                "Source": "admin",
                "Stream_No": 2,
                "Language": "English - ESPN",
                "Quality": "SD",
                "Embed_URL": "https://embedsports.top/embed/admin/ppv-philadelphia-flyers-vs-carolina-hurricanes/2"
            },
            {
                "Source": "golf",
                "Stream_No": 1,
                "Language": "English",
                "Quality": "HD",
                "Embed_URL": "https://embedsports.top/embed/golf/22151/1"
            }
        ]
    },
    {
        "Category": "Baseball",
        "League": "Baseball",
        "Team 1 Name": "New York Yankees",
        "Team 2 Name": "Baltimore Orioles",
        "Team 1 Logo": "https://streamed.pk/api/images/proxy/GwZg7AZpYEZgHCAjAJgCzrAThFlBWSUYAUwVmDW2nmAmD32FrWGHXbeAENgBjUgg5sSdTt0z1Rvdqyw8xAkpj5huYVavAgQ3EBFwhEBvjpCmAJiAsEKTPii5gy8IvNGOmtMM7GiIQA.webp",
        "Team 2 Logo": "https://streamed.pk/api/images/proxy/GwZg7AZpYEZgHCAjAJgCzrAThFlBWSUYAUwVmDW2nmAmD32FrWGHXbeAENgBjUgg5sSdTt0z1Rvdqyw8xAkphTRVfMABMwJENxAQQifTl18QMEFZAEKTPii47y9eaMdNaYHWNEQgA.webp",
        "Match Title": "New York Yankees vs Baltimore Orioles",
        "Match Poster": "https://streamed.pk/api/images/proxy/GwZg7AZpYEZgHCAjAJgCzrAY29lBWSUYAUwVmDTAE5p5gJhqDh61hh1OPgBDYLKQRcOJBt15cyAE1LBCETI3BiOzNCCyaQvENQEgUO7Vq0kQEENKshb8FkgpYRcxijCqUPD+Ub6xXviswGAe4mIQQA.webp",
        "Match Status": "Upcoming ⏳",
        "Start Time": "05:05 AM | 05-May",
        "User-Agent": "Mozilla/5.0 (Windows NT 10.0; Win64; x64)",
        "Streams": [
            {
                "Source": "admin",
                "Stream_No": 1,
                "Language": "English - YES",
                "Quality": "HD",
                "Embed_URL": "https://embedsports.top/embed/admin/ppv-baltimore-orioles-vs-new-york-yankees/1"
            },
            {
                "Source": "admin",
                "Stream_No": 2,
                "Language": "English - YES",
                "Quality": "SD",
                "Embed_URL": "https://embedsports.top/embed/admin/ppv-baltimore-orioles-vs-new-york-yankees/2"
            },
            {
                "Source": "golf",
                "Stream_No": 1,
                "Language": "English",
                "Quality": "HD",
                "Embed_URL": "https://embedsports.top/embed/golf/22157/1"
            }
        ]
    },
    {
        "Category": "Baseball",
        "League": "Baseball",
        "Team 1 Name": "Chicago Cubs",
        "Team 2 Name": "Cincinnati Reds",
        "Team 1 Logo": "https://streamed.pk/api/images/proxy/GwZg7AZpYEZgHCAjAJgCzrAThFlBWSUYAUwVmDW2nmAmD32FrWGHXbeAENgBjUgg5sSdTt0z1Rvdqyw8xAkpj5gQDUiBgg+IbiBK49IEyiOIzEwjGBM+KLmDLwi80Q6a0wTsaIhA.webp",
        "Team 2 Logo": "https://streamed.pk/api/images/proxy/GwZg7AZpYEZgHCAjAJgCzrAThFlBWSUYAUwVmDW2nmAmD32FrWGHXbeAENgBjUgg5sSdTt0z1Rvdqyw8xAkpj7k4ZeNhDcQEEIh0l9IEycSMKTPii5gNReaJtNaYO2NEQgA.webp",
        "Match Title": "Chicago Cubs vs Cincinnati Reds",
        "Match Poster": "https://streamed.pk/api/images/proxy/GwZg7AZpYEZgHCAjAJgCzrAY29lBWSUYAUwVmDTAE5p5gJhqDh61hh1OPgBDYLKQRcOJBt15cyAE1LBCETI3BiOzdmPCMsIeGF4gDO4yBIgIIaZZA2ULJBSwi5jFGFUoe78o2pzP+KzAYO7iYhBAA.webp",
        "Match Status": "Upcoming ⏳",
        "Start Time": "05:40 AM | 05-May",
        "User-Agent": "Mozilla/5.0 (Windows NT 10.0; Win64; x64)",
        "Streams": [
            {
                "Source": "admin",
                "Stream_No": 1,
                "Language": "English - Marquee Sports Net",
                "Quality": "HD",
                "Embed_URL": "https://embedsports.top/embed/admin/ppv-cincinnati-reds-vs-chicago-cubs/1"
            },
            {
                "Source": "admin",
                "Stream_No": 2,
                "Language": "English - Marquee Sports Net",
                "Quality": "SD",
                "Embed_URL": "https://embedsports.top/embed/admin/ppv-cincinnati-reds-vs-chicago-cubs/2"
            },
            {
                "Source": "golf",
                "Stream_No": 1,
                "Language": "English",
                "Quality": "HD",
                "Embed_URL": "https://embedsports.top/embed/golf/22158/1"
            }
        ]
    },
    {
        "Category": "Baseball",
        "League": "Baseball",
        "Team 1 Name": "Kansas City Royals",
        "Team 2 Name": "Cleveland Guardians",
        "Team 1 Logo": "https://streamed.pk/api/images/proxy/GwZg7AZpYEZgHCAjAJgCzrAThFlBWSUYAUwVmDW2nmAmD32FrWGHXbeAENgBjUgg5sSdTt0z1Rvdqyw8xAkhxTsQ8akhDbuIEnpAQQMdSF04AJsYIUmfVWzBkN9eaNVNaYJ2NEQgA.webp",
        "Team 2 Logo": "https://streamed.pk/api/images/proxy/GwZg7AZpYEZgHCAjAJgCzrAThFlBWSUYAUwVmDW2nmAmD32FrWGHXbeAENgBjUgg5sSdTt0z1Rvdqyw8xAkuhDwwSMABN1CtCG4hNICCBggUh4yBLnTBCkz4ouYMmvrzRzprTCuxohBAA.webp",
        "Match Title": "Kansas City Royals vs Cleveland Guardians",
        "Match Poster": "https://streamed.pk/api/images/proxy/GwZg7AZpYEZgHCAjAJgCzrAY29lBWSUYAUwVmDTAE5p5gJhqDh61hh1OPgBDYLKQRcOJBt15cyAE1LBCETI3BiOzdmUTTswJLpC8QWIyZIgIIaZZA2SLJBSwi5jFGFUoe78o2pzP+KzAYO7iYhBAA.webp",
        "Match Status": "Upcoming ⏳",
        "Start Time": "05:40 AM | 05-May",
        "User-Agent": "Mozilla/5.0 (Windows NT 10.0; Win64; x64)",
        "Streams": [
            {
                "Source": "admin",
                "Stream_No": 1,
                "Language": "English - Royals.TV",
                "Quality": "HD",
                "Embed_URL": "https://embedsports.top/embed/admin/ppv-cleveland-guardians-vs-kansas-city-royals/1"
            },
            {
                "Source": "admin",
                "Stream_No": 2,
                "Language": "English - Royals.TV",
                "Quality": "SD",
                "Embed_URL": "https://embedsports.top/embed/admin/ppv-cleveland-guardians-vs-kansas-city-royals/2"
            },
            {
                "Source": "golf",
                "Stream_No": 1,
                "Language": "English",
                "Quality": "HD",
                "Embed_URL": "https://embedsports.top/embed/golf/22159/1"
            }
        ]
    },
    {
        "Category": "Baseball",
        "League": "Baseball",
        "Team 1 Name": "St. Louis Cardinals",
        "Team 2 Name": "Milwaukee Brewers",
        "Team 1 Logo": "https://streamed.pk/api/images/proxy/GwZg7AZpYEZgHCAjAJgCzrAThFlBWSUYAUwVmDW2nmAmD32FrWGHXbeAENgBjUgg5sSdTt0z1Rvdqyw8xAkpjIATMCjDrNObiAi59IGMZCIcfMwQpM+KLmDLwi80faa0wjsaIhA.webp",
        "Team 2 Logo": "https://streamed.pk/api/images/proxy/GwZg7AZpYEZgHCAjAJgCzrAThFlBWSUYAUwVmDW2nmAmD32FrWGHXbeAENgBjUgg5sSdTt0z1Rvdqyw8xAkuhAwQIYAAZQuHiG4gSIFIZB8zpgyfgEKTPii5gy8IvNGOmtMM7GiIQA.webp",
        "Match Title": "St. Louis Cardinals vs Milwaukee Brewers",
        "Match Poster": "https://streamed.pk/api/images/proxy/GwZg7AZpYEZgHCAjAJgCzrAY29lBWSUYAUwVmDTAE5p5gJhqDh61hh1OPgBDYLKQRcOJBt15cyAE1LBCETI3BiOzduBicawJCBQheILMdMkQEENKshbk-LopYRcxijCqUPD+UbU5Xg70YB7iYhBAA.webp",
        "Match Status": "Upcoming ⏳",
        "Start Time": "05:45 AM | 05-May",
        "User-Agent": "Mozilla/5.0 (Windows NT 10.0; Win64; x64)",
        "Streams": [
            {
                "Source": "admin",
                "Stream_No": 1,
                "Language": "English - Cardinals.TV",
                "Quality": "HD",
                "Embed_URL": "https://embedsports.top/embed/admin/ppv-milwaukee-brewers-vs-st-louis-cardinals/1"
            },
            {
                "Source": "admin",
                "Stream_No": 2,
                "Language": "English - Cardinals.TV",
                "Quality": "SD",
                "Embed_URL": "https://embedsports.top/embed/admin/ppv-milwaukee-brewers-vs-st-louis-cardinals/2"
            },
            {
                "Source": "golf",
                "Stream_No": 1,
                "Language": "English",
                "Quality": "HD",
                "Embed_URL": "https://embedsports.top/embed/golf/22160/1"
            }
        ]
    },
    {
        "Category": "Fight",
        "League": "Fight",
        "Team 1 Name": "",
        "Team 2 Name": "",
        "Team 1 Logo": "",
        "Team 2 Logo": "",
        "Match Title": "WWE: Monday Night RAW",
        "Match Poster": "https://streamed.pk/api/images/proxy/GwZg7AZpYEZgHCAjAJgCzuAQ1sFKBWWYgE0OHjBEx0vmAFNp51JQwHguBOdEBkCRCJEJYEJTAIIbjIr8QWedKyDGi7ArFKx3KYpAhxwgxEltwnHsALY8wMOSS4AxpK4cEbPZ0m36YBxSjFJAA.webp",
        "Match Status": "Upcoming ⏳",
        "Start Time": "06:00 AM | 05-May",
        "User-Agent": "Mozilla/5.0 (Windows NT 10.0; Win64; x64)",
        "Streams": [
            {
                "Source": "admin",
                "Stream_No": 1,
                "Language": "English - Netflix",
                "Quality": "HD",
                "Embed_URL": "https://embedsports.top/embed/admin/ppv-wwe-monday-night-raw/1"
            },
            {
                "Source": "admin",
                "Stream_No": 2,
                "Language": "English - Netflix",
                "Quality": "SD",
                "Embed_URL": "https://embedsports.top/embed/admin/ppv-wwe-monday-night-raw/2"
            }
        ]
    },
    {
        "Category": "Basketball",
        "League": "Basketball",
        "Team 1 Name": "New York Knicks",
        "Team 2 Name": "Philadelphia 76ers",
        "Team 1 Logo": "https://streamed.pk/api/images/proxy/GwZg7AZpYEZgHCAjAJgCzrAThFlBWSUYAUwVmDW2nmAmD32FrWGHXbeAENgBjUgg5sSdTt0z1Rvdqyw8xAkpj5gUoWGFEATENxAk9RkEZggIIRMsIxgTPurZby9eaPVNaYLWNEQgA.webp",
        "Team 2 Logo": "https://streamed.pk/api/images/proxy/GwZg7AZpYEZgHCAjAJgCzrAThFlBWSUYAUwVmDW2nmAmD32FrWGHXbeAENgBjUgg5sSdTt0z1Rvdqyw8xAkuhB8Q3ECRARNwACbrNhkNpAGdJnSgIUmfFFzBl4ReaIdNaYJ2NEQgA.webp",
        "Match Title": "New York Knicks vs Philadelphia 76ers",
        "Match Poster": "https://streamed.pk/api/images/proxy/GwZg7AZpYEZgHCAjAJgCzrAThFlBWSUYAUwVmDW2nmAmD32FrWGHXbeAENgBjUgg5sSdTtw5kAJqWCEImeuFFs8rVmylhRWnNxB8QJEClwhEiQ1IMFgSCn2Gz6KbWxRdt5ellkemtGBu9KIQQA.webp",
        "Match Status": "Upcoming ⏳",
        "Start Time": "06:00 AM | 05-May",
        "User-Agent": "Mozilla/5.0 (Windows NT 10.0; Win64; x64)",
        "Streams": [
            {
                "Source": "admin",
                "Stream_No": 1,
                "Language": "English - NBC",
                "Quality": "HD",
                "Embed_URL": "https://embedsports.top/embed/admin/ppv-philadelphia-76-ers-vs-new-york-knicks/1"
            },
            {
                "Source": "admin",
                "Stream_No": 2,
                "Language": "English - NBC",
                "Quality": "SD",
                "Embed_URL": "https://embedsports.top/embed/admin/ppv-philadelphia-76-ers-vs-new-york-knicks/2"
            },
            {
                "Source": "golf",
                "Stream_No": 1,
                "Language": "English",
                "Quality": "HD",
                "Embed_URL": "https://embedsports.top/embed/golf/22150/1"
            }
        ]
    },
    {
        "Category": "Baseball",
        "League": "Baseball",
        "Team 1 Name": "Houston Astros",
        "Team 2 Name": "Los Angeles Dodgers",
        "Team 1 Logo": "https://streamed.pk/api/images/proxy/GwZg7AZpYEZgHCAjAJgCzrAThFlBWSUYAUwVmDW2nmAmD32FrWGHXbeAENgBjUgg5sSdTt0z1Rvdqyw8xAksPZgBKfmBAhuIErh3aQKEIn3b4BCkz4a2YMvCLzRGprTAOxoiEA.webp",
        "Team 2 Logo": "https://streamed.pk/api/images/proxy/GwZg7AZpYEZgHCAjAJgCzrAThFlBWSUYAUwVmDW2nmAmD32FrWGHXbeAENgBjUgg5sSdTt0z1Rvdqyw8xAkphi5KwJCAAmIRN20HEIYyBQg+J+AQpM+KLmDLwi80faa0wjsaIhA.webp",
        "Match Title": "Houston Astros vs Los Angeles Dodgers",
        "Match Poster": "https://streamed.pk/api/images/proxy/GwZg7AZpYEZgHCAjAJgCzrAY29lBWSUYAUwVmDTAE5p5gJhqDh61hh1OPgBDYLKQRcOJBt15cyAE1LBCETI3BiOzdrNm8wSYrxD6sII0ZIgIIaZZA3pLJBSwi5jFGFUoe78o2pzP+KzAYO7iYhBAA.webp",
        "Match Status": "Upcoming ⏳",
        "Start Time": "06:10 AM | 05-May",
        "User-Agent": "Mozilla/5.0 (Windows NT 10.0; Win64; x64)",
        "Streams": [
            {
                "Source": "admin",
                "Stream_No": 1,
                "Language": "English - Space City Home Network",
                "Quality": "HD",
                "Embed_URL": "https://embedsports.top/embed/admin/ppv-los-angeles-dodgers-vs-houston-astros/1"
            },
            {
                "Source": "admin",
                "Stream_No": 2,
                "Language": "English - Space City Home Network",
                "Quality": "SD",
                "Embed_URL": "https://embedsports.top/embed/admin/ppv-los-angeles-dodgers-vs-houston-astros/2"
            },
            {
                "Source": "golf",
                "Stream_No": 1,
                "Language": "English",
                "Quality": "HD",
                "Embed_URL": "https://embedsports.top/embed/golf/22161/1"
            }
        ]
    },
    {
        "Category": "Hockey",
        "League": "Hockey",
        "Team 1 Name": "Anaheim Ducks",
        "Team 2 Name": "Vegas Golden Knights",
        "Team 1 Logo": "",
        "Team 2 Logo": "",
        "Match Title": "Anaheim Ducks vs. Vegas Golden Knights",
        "Match Poster": "https://streamed.pk/api/images/proxy/GwZg7AZpYEZgHCAjAJgCzuAQ1sFKBWWYgE0OHjBEx0vmAFNp51JQwHguBOdELEDBDCQ2YBGAls-EAGNg3BdQoLJIRfSwU5jbUO4yG64WPq9gbcJx7ACYlBfJJcsh1w4I2izg7v0wHOK6EEA.webp",
        "Match Status": "Upcoming ⏳",
        "Start Time": "07:30 AM | 05-May",
        "User-Agent": "Mozilla/5.0 (Windows NT 10.0; Win64; x64)",
        "Streams": [
            {
                "Source": "admin",
                "Stream_No": 1,
                "Language": "English - ESPN",
                "Quality": "HD",
                "Embed_URL": "https://embedsports.top/embed/admin/ppv-anaheim-ducks-vs-vegas-golden-knights/1"
            },
            {
                "Source": "admin",
                "Stream_No": 2,
                "Language": "English - ESPN",
                "Quality": "SD",
                "Embed_URL": "https://embedsports.top/embed/admin/ppv-anaheim-ducks-vs-vegas-golden-knights/2"
            },
            {
                "Source": "golf",
                "Stream_No": 1,
                "Language": "English",
                "Quality": "HD",
                "Embed_URL": "https://embedsports.top/embed/golf/22152/1"
            }
        ]
    },
    {
        "Category": "Basketball",
        "League": "Basketball",
        "Team 1 Name": "San Antonio Spurs",
        "Team 2 Name": "Minnesota Timberwolves",
        "Team 1 Logo": "https://streamed.pk/api/images/proxy/GwZg7AZpYEZgHCAjAJgCzrAThFlBWSUYAUwVmDW2nmAmD32FrWGHXbeAENgBjUgg5sSdTt0z1Rvdqyw8xAkhzlhRtXvhDcQAE20GQIEiBTGQiPgQpMrXNeXrzRKYE1pg1Y0RCA.webp",
        "Team 2 Logo": "https://streamed.pk/api/images/proxy/GwZg7AZpYEZgHCAjAJgCzrAThFlBWSUYAUwVmDW2nmAmD32FrWGHXbeAENgBjUgg5sSdTt0z1Rvdqyw8xAkuhBlwMfsCT8Q3EABNcu1SBQgIIPpd0EKTPii5gy8IvNGOmtMM7GiIQA.webp",
        "Match Title": "San Antonio Spurs vs Minnesota Timberwolves",
        "Match Poster": "https://streamed.pk/api/images/proxy/GwZg7AZpYEZgHCAjAJgCzrAThFlBWSUYAUwVmDW2nmAmD32FrWGHXbeAENgBjUgg5sSdTtw5kAJqWCEImeuFFs8VXiBBSQiTTBDcQfECRApcOy+YhmCwJBT7DZ9FGBUou78vSyzPTLRg7mKiEEA.webp",
        "Match Status": "Upcoming ⏳",
        "Start Time": "07:30 AM | 05-May",
        "User-Agent": "Mozilla/5.0 (Windows NT 10.0; Win64; x64)",
        "Streams": [
            {
                "Source": "admin",
                "Stream_No": 1,
                "Language": "English - NBCSN",
                "Quality": "HD",
                "Embed_URL": "https://embedsports.top/embed/admin/ppv-minnesota-timberwolves-vs-san-antonio-spurs/1"
            },
            {
                "Source": "admin",
                "Stream_No": 2,
                "Language": "English - NBCSN",
                "Quality": "SD",
                "Embed_URL": "https://embedsports.top/embed/admin/ppv-minnesota-timberwolves-vs-san-antonio-spurs/2"
            },
            {
                "Source": "golf",
                "Stream_No": 1,
                "Language": "English",
                "Quality": "HD",
                "Embed_URL": "https://embedsports.top/embed/golf/22149/1"
            }
        ]
    },
    {
        "Category": "Baseball",
        "League": "Baseball",
        "Team 1 Name": "Los Angeles Angels",
        "Team 2 Name": "Chicago White Sox",
        "Team 1 Logo": "https://streamed.pk/api/images/proxy/GwZg7AZpYEZgHCAjAJgCzrAThFlBWSUYAUwVmDW2nmAmD32FrWGHXbeAENgBjUgg5sSdTt0z1Rvdqyw8xAkpgAm5PuTUgQ3EBBCIcJEHxN6zKghSZ8UXMGXhF5ou01pgHY0RCA.webp",
        "Team 2 Logo": "https://streamed.pk/api/images/proxy/GwZg7AZpYEZgHCAjAJgCzrAThFlBWSUYAUwVmDW2nmAmD32FrWGHXbeAENgBjUgg5sSdTt0z1Rvdqyw8xAkphRhVSEKPogQ3Tfoi6QhmDrMQCFJnxRcwZeEXmjbTWmHtitQA.webp",
        "Match Title": "Los Angeles Angels vs Chicago White Sox",
        "Match Poster": "https://streamed.pk/api/images/proxy/GwZg7AZpYEZgHCAjAJgCzrAY29lBWSUYAUwVmDTAE5p5gJhqDh61hh1OPgBDYLKQRcOJBt15cyAE1LBCETI3BiOzKokGMw0aiF4gsh4yRAQQ0iyBQgYLJBSwi5jFGFUoe78o2pzP+KzAOmKMoUA.webp",
        "Match Status": "Upcoming ⏳",
        "Start Time": "07:38 AM | 05-May",
        "User-Agent": "Mozilla/5.0 (Windows NT 10.0; Win64; x64)",
        "Streams": [
            {
                "Source": "admin",
                "Stream_No": 1,
                "Language": "English - KCOP",
                "Quality": "HD",
                "Embed_URL": "https://embedsports.top/embed/admin/ppv-chicago-white-sox-vs-los-angeles-angels/1"
            },
            {
                "Source": "admin",
                "Stream_No": 2,
                "Language": "English - KCOP",
                "Quality": "SD",
                "Embed_URL": "https://embedsports.top/embed/admin/ppv-chicago-white-sox-vs-los-angeles-angels/2"
            },
            {
                "Source": "golf",
                "Stream_No": 1,
                "Language": "English",
                "Quality": "HD",
                "Embed_URL": "https://embedsports.top/embed/golf/22163/1"
            }
        ]
    },
    {
        "Category": "Baseball",
        "League": "Baseball",
        "Team 1 Name": "Seattle Mariners",
        "Team 2 Name": "Atlanta Braves",
        "Team 1 Logo": "https://streamed.pk/api/images/proxy/GwZg7AZpYEZgHCAjAJgCzrAThFlBWSUYAUwVmDW2nmAmD32FrWGHXbeAENgBjUgg5sSdTt0z1Rvdqyw8xAkuhCIUYECHUxQIbiBK49WkDFUnE8AhSZ8UXMGXhF5o+01phHY0RCA.webp",
        "Team 2 Logo": "https://streamed.pk/api/images/proxy/GwZg7AZpYEZgHCAjAJgCzrAThFlBWSUYAUwVmDW2nmAmD32FrWGHXbeAENgBjUgg5sSdTt0z1Rvdqyw8xAkphTAkCEHxAATUiG479mkCYMGIIFDoIUmfVWzBl4ReaNVNaYJ2NEQgA.webp",
        "Match Title": "Seattle Mariners vs Atlanta Braves",
        "Match Poster": "https://streamed.pk/api/images/proxy/GwZg7AZpYEZgHCAjAJgCzrAY29lBWSUYAUwVmDTAE5p5gJhqDh61hh1OPgBDYLKQRcOJBt15cyAE1LBCETI3BiOzNCHhheIWklawQOrCBMmSICCGnWQd5vmBIKWEXMYowqlDy-lG1HI+jvRgXuJiEEA.webp",
        "Match Status": "Upcoming ⏳",
        "Start Time": "07:40 AM | 05-May",
        "User-Agent": "Mozilla/5.0 (Windows NT 10.0; Win64; x64)",
        "Streams": [
            {
                "Source": "admin",
                "Stream_No": 1,
                "Language": "English - Mariners.TV",
                "Quality": "HD",
                "Embed_URL": "https://embedsports.top/embed/admin/ppv-atlanta-braves-vs-seattle-mariners/1"
            },
            {
                "Source": "admin",
                "Stream_No": 2,
                "Language": "English - Mariners.TV",
                "Quality": "SD",
                "Embed_URL": "https://embedsports.top/embed/admin/ppv-atlanta-braves-vs-seattle-mariners/2"
            },
            {
                "Source": "golf",
                "Stream_No": 1,
                "Language": "English",
                "Quality": "HD",
                "Embed_URL": "https://embedsports.top/embed/golf/22164/1"
            }
        ]
    },
    {
        "Category": "Baseball",
        "League": "Baseball",
        "Team 1 Name": "San Francisco Giants",
        "Team 2 Name": "San Diego Padres",
        "Team 1 Logo": "https://streamed.pk/api/images/proxy/GwZg7AZpYEZgHCAjAJgCzrAThFlBWSUYAUwVmDW2nmAmD32FrWGHXbeAENgBjUgg5sSdTt0z1Rvdqyw8xAksLDcQ67mBQMQakrl3qQKEABMzBxhSZ9tbMGXhF5o7U1pgHY0RCA.webp",
        "Team 2 Logo": "https://streamed.pk/api/images/proxy/GwZg7AZpYEZgHCAjAJgCzrAThFlBWSUYAUwVmDW2nmAmD32FrWGHXbeAENgBjUgg5sSdTt0z1Rvdqyw8xAkuhAATMH0ghetfNrX6+IErhBGTiGAQpM+KLmDLwi80faa0wjsaIhA.webp",
        "Match Title": "San Francisco Giants vs San Diego Padres",
        "Match Poster": "https://streamed.pk/api/images/proxy/GwZg7AZpYEZgHCAjAJgCzrAY29lBWSUYAUwVmDTAE5p5gJhqDh61hh1OPgBDYLKQRcOJBt15cyAE1LBCETI3BiOzdgAYQUWiD6wQvEFmOmS2kNMsgbi-MCQUsIuYxRhVKHh-KNqcr3t6MA9xMQggA.webp",
        "Match Status": "Upcoming ⏳",
        "Start Time": "07:45 AM | 05-May",
        "User-Agent": "Mozilla/5.0 (Windows NT 10.0; Win64; x64)",
        "Streams": [
            {
                "Source": "admin",
                "Stream_No": 1,
                "Language": "English - NBC Sports BA",
                "Quality": "HD",
                "Embed_URL": "https://embedsports.top/embed/admin/ppv-san-diego-padres-vs-san-francisco-giants/1"
            },
            {
                "Source": "admin",
                "Stream_No": 2,
                "Language": "English - NBC Sports BA",
                "Quality": "SD",
                "Embed_URL": "https://embedsports.top/embed/admin/ppv-san-diego-padres-vs-san-francisco-giants/2"
            },
            {
                "Source": "golf",
                "Stream_No": 1,
                "Language": "English",
                "Quality": "HD",
                "Embed_URL": "https://embedsports.top/embed/golf/22165/1"
            }
        ]
    }
]